gemini_starter_agent/__init__.py
gemini_starter_agent/main.py
gemini_starter_agent-0.1.2.dist-info/licenses/LICENSE.md
gemini_starter_agent-0.1.2.dist-info/METADATA
gemini_starter_agent-0.1.2.dist-info/WHEEL
gemini_starter_agent-0.1.2.dist-info/entry_points.txt
gemini_starter_agent-0.1.2.dist-info/top_level.txt
gemini_starter_agent-0.1.2.dist-info/RECORD
