Metadata-Version: 2.4
Name: gemini-starter-agent
Version: 0.1.2
Summary: A CLI tool to bootstrap Gemini agents with OpenAI Agent SDK using UV.
Author: Marjan Ahmed
Author-email: marjanahmed.dev@gmail.com
Requires-Python: >=3.13
License-File: LICENSE.md
Requires-Dist: python-dotenv
Requires-Dist: InquirerPy
Dynamic: author
Dynamic: author-email
Dynamic: description
Dynamic: description-content-type
Dynamic: license-file
Dynamic: requires-dist
Dynamic: requires-python
Dynamic: summary
